{
    "badlands": ["badlands", "eroded badlands", "wooded badlands"],
    "basalt": ["basalt deltas"],
    "crimson": ["crimson forest"],
    "dark_forest": ["dark forest"],
    "deep_dark": ["deep dark"],
    "default": [
        "birch forest",
        "old growth birch forest",
        "plains",
        "forest",
        "stony shore",
        "beach",
        "river"
    ],
    "desert": ["desert"],
    "dripstone": ["dripstone caves"],
    "end": ["dimension: the end"],
    "flower": [
        "flower forest",
        "sunflower plains",
        "meadow",
        "cherry grove",
        "sunflower plains"
    ],
    "ice": ["snowy beach", "snowy plains", "ice spikes", "frozen river"],
    "jungle": ["bamboo jungle", "jungle", "sparse jungle"],
    "lush_caves": ["lush caves"],
    "mountain": [
        "frozen peaks",
        "jagged peaks",
        "stony peaks",
        "snowy slopes",
        "grove"
    ],
    "mushroom": ["mushroom fields"],
    "nether": ["nether wastes"],
    "ocean": [
        "deep frozen ocean",
        "deep cold ocean",
        "deep ocean",
        "deep lukewarm ocean",
        "frozen ocean",
        "ocean",
        "cold ocean",
        "lukewarm ocean",
        "warm ocean"
    ],
    "savanna": ["savanna", "savanna plateau", "windswept savanna"],
    "soul_valley": ["soul sand valley"],
    "swamp": ["swamp", "mangrove swamp"],
    "taiga": [
        "taiga",
        "snowy taiga",
        "old growth pine taiga",
        "old growth spruce taiga"
    ],
    "warped": ["warped forest"],
    "wind": ["windswept hills", "windswept forest", "windswept gravelly hills"]
}
